Jenkinsfile
MANIFEST.in
Makefile
README.md
hassmpris-client.spec
mypy.ini
pyproject.toml
setup.cfg
tox.ini
src/hassmpris_client/__init__.py
src/hassmpris_client/cli.py
src/hassmpris_client/py.typed
src/hassmpris_client.egg-info/PKG-INFO
src/hassmpris_client.egg-info/SOURCES.txt
src/hassmpris_client.egg-info/dependency_links.txt
src/hassmpris_client.egg-info/entry_points.txt
src/hassmpris_client.egg-info/requires.txt
src/hassmpris_client.egg-info/top_level.txt
tests/conftest.py
tests/test_dummy.py