Metadata-Version: 2.2
Name: hassmpris_client
Version: 0.0.27
Summary: Simple command-line client to control the MPRIS multimedia agent
Home-page: https://github.com/Rudd-O/hassmpris
Author: Manuel Amador (Rudd-O)
Author-email: rudd-o@rudd-o.com
Classifier: Programming Language :: Python :: 3
Classifier: License :: OSI Approved :: GNU Lesser General Public License v2 (LGPLv2)
Requires-Dist: cryptography
Requires-Dist: blindecdh>=0.1.9
Requires-Dist: shortauthstrings>=0.1.8
Requires-Dist: cakes>=0.1.7
Requires-Dist: hassmpris>=0.1.18
